<?xml version = '1.0' encoding = 'UTF-8'?>
<!DOCTYPE properties SYSTEM "http://java.sun.com/dtd/properties.dtd">
<properties>
   <entry key="API_BUNDLE_TRANS.PART_CODE:db_column_not_null">false</entry>
   <entry key="API_BUNDLE_TRANS.PROCESSED:db_column_not_null">true</entry>
   <entry key="API_BUNDLE_TRANS.BILLET_BATCH:db_column_size">12</entry>
   <entry key="API_BUNDLE_TRANS.PART_CODE_FROM:db_column_type">VARCHAR2</entry>
   <entry key="API_BUNDLE_TRANS.HOLD_CODE_2:db_column_not_null">false</entry>
   <entry key="API_BUNDLE_TRANS.STACK:db_column_not_null">false</entry>
   <entry key="API_BUNDLE_TRANS.MELT_HEAT:db_column_type">VARCHAR2</entry>
   <entry key="API_BUNDLE_TRANS.LENGTH_INCHES:db_column_type">NUMBER</entry>
   <entry key="API_BUNDLE_TRANS.JOB_NUMBER:db_column_not_null">false</entry>
   <entry key="API_BUNDLE_TRANS:db_table_type">TABLE</entry>
   <entry key="API_BUNDLE_TRANS.USER_FIRST_NAME:db_column_not_null">false</entry>
   <entry key="API_BUNDLE_TRANS.HOLD_CODE_3:db_column_size">10</entry>
   <entry key="API_BUNDLE_TRANS.MELT_PRACTICE:db_column_not_null">false</entry>
   <entry key="API_BUNDLE_TRANS.PIECE_COUNT:db_column_type">NUMBER</entry>
   <entry key="API_BUNDLE_TRANS.TRANSACTION_TYPE:db_column_size">15</entry>
   <entry key="API_BUNDLE_TRANS.BILLET_BATCH:db_column_not_null">false</entry>
   <entry key="API_BUNDLE_TRANS.HOLD_CODE_3_FROM:db_column_not_null">false</entry>
   <entry key="API_BUNDLE_TRANS.MELT_PRACTICE:db_column_type">VARCHAR2</entry>
   <entry key="API_BUNDLE_TRANS.TRANSACTION_DATE:db_column_not_null">false</entry>
   <entry key="API_BUNDLE_TRANS.DISPOSITION:db_column_type">VARCHAR2</entry>
   <entry key="API_BUNDLE_TRANS.PROCESS_DATE:db_column_not_null">false</entry>
   <entry key="API_BUNDLE_TRANS.HOLD_CODE_1:db_column_type">VARCHAR2</entry>
   <entry key="API_BUNDLE_TRANS.MELT_HEAT:db_column_not_null">false</entry>
   <entry key="API_BUNDLE_TRANS.TAG_NO:db_column_size">15</entry>
   <entry key="API_BUNDLE_TRANS.PART_CODE_FROM:db_column_size">15</entry>
   <entry key="API_BUNDLE_TRANS.ERROR_MESSAGE:db_column_type">VARCHAR2</entry>
   <entry key="API_BUNDLE_TRANS.SHIFT:db_column_type">NUMBER</entry>
   <entry key="API_BUNDLE_TRANS.HOLD_CODE_5_FROM:db_column_type">VARCHAR2</entry>
   <entry key="API_BUNDLE_TRANS.MELT_HEAT:db_column_size">15</entry>
   <entry key="API_BUNDLE_TRANS.BUNDLE_SIZE:db_column_type">VARCHAR2</entry>
   <entry key="API_BUNDLE_TRANS.MILL_HEAT:db_column_type">VARCHAR2</entry>
   <entry key="API_BUNDLE_TRANS.PIECE_COUNT:db_column_not_null">false</entry>
   <entry key="API_BUNDLE_TRANS.HOLD_CODE_3:db_column_not_null">false</entry>
   <entry key="API_BUNDLE_TRANS.SHIFT:db_column_precision">1</entry>
   <entry key="API_BUNDLE_TRANS.MELT_PRACTICE:db_column_size">15</entry>
   <entry key="API_BUNDLE_TRANS.HOLD_CODE_4_FROM:db_column_type">VARCHAR2</entry>
   <entry key="API_BUNDLE_TRANS.PART_CODE:db_column_type">VARCHAR2</entry>
   <entry key="API_BUNDLE_TRANS.PRODUCTION_DATE:db_column_type">DATE</entry>
   <entry key="API_BUNDLE_TRANS.PROCESSED:db_column_type">VARCHAR2</entry>
   <entry key="API_BUNDLE_TRANS.DISPOSITION:db_column_size">15</entry>
   <entry key="API_BUNDLE_TRANS.HOLD_CODE_1:db_column_size">10</entry>
   <entry key="API_BUNDLE_TRANS.BUNDLE_SIZE:db_column_not_null">false</entry>
   <entry key="API_BUNDLE_TRANS.GRADE:db_column_not_null">false</entry>
   <entry key="API_BUNDLE_TRANS.HOLD_CODE_4_FROM:db_column_not_null">false</entry>
   <entry key="API_BUNDLE_TRANS.ERROR_MESSAGE:db_column_size">2000</entry>
   <entry key="API_BUNDLE_TRANS:db_column_40">BILLET_BATCH</entry>
   <entry key="API_BUNDLE_TRANS:db_column_9">GRADE</entry>
   <entry key="API_BUNDLE_TRANS:db_column_8">BUNDLE_SIZE</entry>
   <entry key="API_BUNDLE_TRANS.HOLD_CODE_5_FROM:db_column_size">10</entry>
   <entry key="API_BUNDLE_TRANS:db_column_7">SHAPE</entry>
   <entry key="API_BUNDLE_TRANS.HOLD_CODE_3_FROM:db_column_type">VARCHAR2</entry>
   <entry key="API_BUNDLE_TRANS:db_column_6">PART_CODE</entry>
   <entry key="API_BUNDLE_TRANS:db_column_5">PART_CODE_FROM</entry>
   <entry key="API_BUNDLE_TRANS:db_column_4">MELT_HEAT</entry>
   <entry key="API_BUNDLE_TRANS:db_column_3">MILL_HEAT</entry>
   <entry key="API_BUNDLE_TRANS.DISPOSITION_FROM:db_column_type">VARCHAR2</entry>
   <entry key="API_BUNDLE_TRANS:db_column_2">TAG_NO</entry>
   <entry key="API_BUNDLE_TRANS:db_column_1">TRANSACTION_TYPE</entry>
   <entry key="API_BUNDLE_TRANS:db_column_0">ID</entry>
   <entry key="API_BUNDLE_TRANS.BUNDLE_SIZE:db_column_size">25</entry>
   <entry key="API_BUNDLE_TRANS.MILL_HEAT:db_column_size">15</entry>
   <entry key="API_BUNDLE_TRANS.GRADE:db_column_type">VARCHAR2</entry>
   <entry key="API_BUNDLE_TRANS:db_column_39">ERROR_MESSAGE</entry>
   <entry key="API_BUNDLE_TRANS:db_column_38">TRANSACTION_DATE</entry>
   <entry key="API_BUNDLE_TRANS.USER_LAST_NAME:db_column_not_null">false</entry>
   <entry key="API_BUNDLE_TRANS:db_column_37">JOB_NUMBER</entry>
   <entry key="API_BUNDLE_TRANS:db_column_36">CREATE_DATE</entry>
   <entry key="API_BUNDLE_TRANS.HOLD_CODE_4_FROM:db_column_size">10</entry>
   <entry key="API_BUNDLE_TRANS.HOLD_CODE_2_FROM:db_column_type">VARCHAR2</entry>
   <entry key="API_BUNDLE_TRANS.PART_CODE:db_column_size">15</entry>
   <entry key="API_BUNDLE_TRANS:db_column_35">PROCESS_DATE</entry>
   <entry key="API_BUNDLE_TRANS:db_column_34">PROCESSED</entry>
   <entry key="API_BUNDLE_TRANS:db_column_33">HOLD_CODE_5</entry>
   <entry key="API_BUNDLE_TRANS:db_column_32">HOLD_CODE_4</entry>
   <entry key="API_BUNDLE_TRANS.SHAPE:db_column_not_null">false</entry>
   <entry key="API_BUNDLE_TRANS:db_column_31">HOLD_CODE_3</entry>
   <entry key="API_BUNDLE_TRANS.HOLD_CODE_4:db_column_type">VARCHAR2</entry>
   <entry key="API_BUNDLE_TRANS.PROCESSED:db_column_size">1</entry>
   <entry key="API_BUNDLE_TRANS:db_column_30">HOLD_CODE_2</entry>
   <entry key="API_BUNDLE_TRANS.ID:db_column_scale">0</entry>
   <entry key="API_BUNDLE_TRANS.HOLD_CODE_4:db_column_not_null">false</entry>
   <entry key="API_BUNDLE_TRANS.HOLD_CODE_3_FROM:db_column_size">10</entry>
   <entry key="API_BUNDLE_TRANS.HOLD_CODE_1_FROM:db_column_type">VARCHAR2</entry>
   <entry key="API_BUNDLE_TRANS.MILL_HEAT:db_column_not_null">false</entry>
   <entry key="API_BUNDLE_TRANS:db_column_29">HOLD_CODE_1</entry>
   <entry key="API_BUNDLE_TRANS.DISPOSITION_FROM:db_column_size">15</entry>
   <entry key="API_BUNDLE_TRANS:db_column_28">HOLD_CODE_5_FROM</entry>
   <entry key="API_BUNDLE_TRANS:db_column_27">HOLD_CODE_4_FROM</entry>
   <entry key="API_BUNDLE_TRANS:db_column_26">HOLD_CODE_3_FROM</entry>
   <entry key="API_BUNDLE_TRANS:db_column_25">HOLD_CODE_2_FROM</entry>
   <entry key="API_BUNDLE_TRANS:db_column_24">HOLD_CODE_1_FROM</entry>
   <entry key="API_BUNDLE_TRANS:db_column_23">USER_LAST_NAME</entry>
   <entry key="API_BUNDLE_TRANS:db_column_22">USER_FIRST_NAME</entry>
   <entry key="API_BUNDLE_TRANS.HOLD_CODE_5_FROM:db_column_not_null">false</entry>
   <entry key="API_BUNDLE_TRANS:db_column_21">USER_ID</entry>
   <entry key="API_BUNDLE_TRANS:db_column_20">PRODUCTION_DATE</entry>
   <entry key="API_BUNDLE_TRANS.GRADE:db_column_size">15</entry>
   <entry key="API_BUNDLE_TRANS.CREW:db_column_not_null">false</entry>
   <entry key="API_BUNDLE_TRANS.HOLD_CODE_2_FROM:db_column_size">10</entry>
   <entry key="API_BUNDLE_TRANS.HOLD_CODE_4:db_column_size">10</entry>
   <entry key="API_BUNDLE_TRANS.JOB_NUMBER:db_column_type">VARCHAR2</entry>
   <entry key="API_BUNDLE_TRANS.CREATE_DATE:db_column_type">DATE</entry>
   <entry key="API_BUNDLE_TRANS:db_column_19">SHIFT</entry>
   <entry key="API_BUNDLE_TRANS:db_column_18">CREW</entry>
   <entry key="API_BUNDLE_TRANS:db_column_17">WEIGHT_LBS</entry>
   <entry key="API_BUNDLE_TRANS:db_column_16">PIECE_COUNT</entry>
   <entry key="API_BUNDLE_TRANS:db_column_15">DISPOSITION</entry>
   <entry key="API_BUNDLE_TRANS:db_column_14">DISPOSITION_FROM</entry>
   <entry key="API_BUNDLE_TRANS:db_column_13">STACK</entry>
   <entry key="API_BUNDLE_TRANS:db_column_12">STACK_FROM</entry>
   <entry key="API_BUNDLE_TRANS:db_column_11">LENGTH_INCHES</entry>
   <entry key="API_BUNDLE_TRANS.LENGTH_INCHES:db_column_scale">0</entry>
   <entry key="API_BUNDLE_TRANS:db_column_10">MELT_PRACTICE</entry>
   <entry key="API_BUNDLE_TRANS.HOLD_CODE_1_FROM:db_column_size">10</entry>
   <entry key="API_BUNDLE_TRANS.SHAPE:db_column_type">VARCHAR2</entry>
   <entry key="API_BUNDLE_TRANS.TRANSACTION_DATE:db_column_type">DATE</entry>
   <entry key="API_BUNDLE_TRANS.HOLD_CODE_2:db_column_type">VARCHAR2</entry>
   <entry key="API_BUNDLE_TRANS.SHIFT:db_column_scale">0</entry>
   <entry key="API_BUNDLE_TRANS.STACK_FROM:db_column_type">VARCHAR2</entry>
   <entry key="API_BUNDLE_TRANS.USER_ID:db_column_type">VARCHAR2</entry>
   <entry key="API_BUNDLE_TRANS.HOLD_CODE_5:db_column_not_null">false</entry>
   <entry key="API_BUNDLE_TRANS.CREW:db_column_type">VARCHAR2</entry>
   <entry key="API_BUNDLE_TRANS.USER_FIRST_NAME:db_column_type">VARCHAR2</entry>
   <entry key="API_BUNDLE_TRANS.USER_LAST_NAME:db_column_type">VARCHAR2</entry>
   <entry key="API_BUNDLE_TRANS.JOB_NUMBER:db_column_size">15</entry>
   <entry key="API_BUNDLE_TRANS.ID:db_column_not_null">true</entry>
   <entry key="API_BUNDLE_TRANS.SHAPE:db_column_size">15</entry>
   <entry key="API_BUNDLE_TRANS.PART_CODE_FROM:db_column_not_null">false</entry>
   <entry key="API_BUNDLE_TRANS.ID:db_column_type">NUMBER</entry>
   <entry key="API_BUNDLE_TRANS.TRANSACTION_TYPE:db_column_not_null">true</entry>
   <entry key="API_BUNDLE_TRANS.WEIGHT_LBS:db_column_type">NUMBER</entry>
   <entry key="API_BUNDLE_TRANS.HOLD_CODE_2:db_column_size">10</entry>
   <entry key="API_BUNDLE_TRANS.STACK_FROM:db_column_size">20</entry>
   <entry key="API_BUNDLE_TRANS.DISPOSITION_FROM:db_column_not_null">false</entry>
   <entry key="API_BUNDLE_TRANS.PROCESS_DATE:db_column_type">DATE</entry>
   <entry key="API_BUNDLE_TRANS.TAG_NO:db_column_not_null">true</entry>
   <entry key="API_BUNDLE_TRANS.USER_ID:db_column_size">15</entry>
   <entry key="API_BUNDLE_TRANS.CREW:db_column_size">1</entry>
   <entry key="API_BUNDLE_TRANS.USER_FIRST_NAME:db_column_size">25</entry>
   <entry key="API_BUNDLE_TRANS.WEIGHT_LBS:db_column_precision">10</entry>
   <entry key="API_BUNDLE_TRANS.USER_LAST_NAME:db_column_size">25</entry>
   <entry key="root_descriptor_alias">API_BUNDLE_TRANS</entry>
   <entry key="API_BUNDLE_TRANS.LENGTH_INCHES:db_column_precision">10</entry>
   <entry key="API_BUNDLE_TRANS.ERROR_MESSAGE:db_column_not_null">false</entry>
   <entry key="API_BUNDLE_TRANS.HOLD_CODE_1_FROM:db_column_not_null">false</entry>
   <entry key="API_BUNDLE_TRANS.WEIGHT_LBS:db_column_scale">0</entry>
   <entry key="API_BUNDLE_TRANS.ID:db_column_precision">20</entry>
   <entry key="API_BUNDLE_TRANS.HOLD_CODE_5:db_column_type">VARCHAR2</entry>
   <entry key="API_BUNDLE_TRANS.STACK:db_column_type">VARCHAR2</entry>
   <entry key="API_BUNDLE_TRANS.PRODUCTION_DATE:db_column_not_null">false</entry>
   <entry key="API_BUNDLE_TRANS.CREATE_DATE:db_column_not_null">true</entry>
   <entry key="API_BUNDLE_TRANS.HOLD_CODE_1:db_column_not_null">false</entry>
   <entry key="API_BUNDLE_TRANS.WEIGHT_LBS:db_column_not_null">false</entry>
   <entry key="API_BUNDLE_TRANS.STACK_FROM:db_column_not_null">false</entry>
   <entry key="API_BUNDLE_TRANS.PIECE_COUNT:db_column_scale">0</entry>
   <entry key="API_BUNDLE_TRANS.SHIFT:db_column_not_null">false</entry>
   <entry key="API_BUNDLE_TRANS.HOLD_CODE_5:db_column_size">10</entry>
   <entry key="API_BUNDLE_TRANS.STACK:db_column_size">20</entry>
   <entry key="API_BUNDLE_TRANS.BILLET_BATCH:db_column_type">VARCHAR2</entry>
   <entry key="API_BUNDLE_TRANS.USER_ID:db_column_not_null">true</entry>
   <entry key="API_BUNDLE_TRANS.HOLD_CODE_2_FROM:db_column_not_null">false</entry>
   <entry key="API_BUNDLE_TRANS.LENGTH_INCHES:db_column_not_null">false</entry>
   <entry key="API_BUNDLE_TRANS.DISPOSITION:db_column_not_null">false</entry>
   <entry key="API_BUNDLE_TRANS.HOLD_CODE_3:db_column_type">VARCHAR2</entry>
   <entry key="API_BUNDLE_TRANS.TRANSACTION_TYPE:db_column_type">VARCHAR2</entry>
   <entry key="API_BUNDLE_TRANS.PIECE_COUNT:db_column_precision">3</entry>
   <entry key="API_BUNDLE_TRANS.TAG_NO:db_column_type">VARCHAR2</entry>
</properties>